mortal_reactpy/__init__.py
mortal_reactpy/reactpy_flask.pyd
mortal_reactpy/reactpy_flask.so
mortal_reactpy/reactpy_main.pyd
mortal_reactpy/reactpy_main.so
mortal_reactpy/reactpy_parse.pyd
mortal_reactpy/reactpy_parse.so
mortal_reactpy/static/assets/index.html
mortal_reactpy/static/assets/mortal-reactpy-logo.ico
mortal_reactpy-2.3.27.dist-info/METADATA
mortal_reactpy-2.3.27.dist-info/WHEEL
mortal_reactpy-2.3.27.dist-info/top_level.txt
mortal_reactpy-2.3.27.dist-info/RECORD
