Metadata-Version: 2.1
Name: mortal_reactpy
Version: 2.3.27
Summary: 'mortal工具集::reactpy'
Author: MJ
Requires-Python: <=3.11,>=3.10
Requires-Dist: reactpy
Requires-Dist: flask
Requires-Dist: flask-cors
Requires-Dist: flask-sock
Requires-Dist: requests
Requires-Dist: mortal-var
Requires-Dist: mortal-timer
Requires-Dist: mortal-log
Requires-Dist: bs4
